aiwflow/JiraService.py
aiwflow/Spinner.py
aiwflow/__init__.py
aiwflow/config.py
aiwflow/llm.py
aiwflow/main.py
aiwflow/util.py
aiwflow-0.5.3.dist-info/LICENSE
aiwflow-0.5.3.dist-info/METADATA
aiwflow-0.5.3.dist-info/WHEEL
aiwflow-0.5.3.dist-info/entry_points.txt
aiwflow-0.5.3.dist-info/RECORD
