Metadata-Version: 2.1
Name: aiwflow
Version: 0.5.3
Summary: Optimize your workflow effortlessly using with jira and github, seamlessly integrating with the power of OpenAI API.
License: LICENSE
Author: wangym
Author-email: wangym0203@gmail.com
Requires-Python: >=3.8
Classifier: License :: Other/Proprietary License
Classifier: Programming Language :: Python :: 3
Classifier: Programming Language :: Python :: 3.8
Classifier: Programming Language :: Python :: 3.9
Classifier: Programming Language :: Python :: 3.10
Classifier: Programming Language :: Python :: 3.11
Classifier: Programming Language :: Python :: 3.12
Requires-Dist: httpx[socks] (>=0.24.0)
Requires-Dist: jira[cli] (>=3.5.2,<4.0.0)
Requires-Dist: openai (>=1.5.0,<2.0.0)
Requires-Dist: typer (>=0.9.0,<0.10.0)
